cfnlint/__init__.py
cfnlint/__main__.py
cfnlint/api.py
cfnlint/config.py
cfnlint/core.py
cfnlint/exceptions.py
cfnlint/graph.py
cfnlint/helpers.py
cfnlint/languageExtensions.py
cfnlint/maintenance.py
cfnlint/match.py
cfnlint/runner.py
cfnlint/transform.py
cfnlint/version.py
cfnlint/conditions/__init__.py
cfnlint/conditions/_utils.py
cfnlint/conditions/condition.py
cfnlint/conditions/conditions.py
cfnlint/conditions/equals.py
cfnlint/data/__init__.py
cfnlint/data/AdditionalSpecs/AtLeastOne.json
cfnlint/data/AdditionalSpecs/BasedOnValue.json
cfnlint/data/AdditionalSpecs/Exclusive.json
cfnlint/data/AdditionalSpecs/Inclusive.json
cfnlint/data/AdditionalSpecs/LmbdRuntimeLifecycle.json
cfnlint/data/AdditionalSpecs/OnlyOne.json
cfnlint/data/AdditionalSpecs/Policies.json
cfnlint/data/AdditionalSpecs/RdsProperties.json
cfnlint/data/AdditionalSpecs/StatefulResources.json
cfnlint/data/AdditionalSpecs/__init__.py
cfnlint/data/CfnLintCli/config/schema.json
cfnlint/data/CloudSpecs/__init__.py
cfnlint/data/CloudSpecs/af-south-1.json
cfnlint/data/CloudSpecs/ap-east-1.json
cfnlint/data/CloudSpecs/ap-northeast-1.json
cfnlint/data/CloudSpecs/ap-northeast-2.json
cfnlint/data/CloudSpecs/ap-northeast-3.json
cfnlint/data/CloudSpecs/ap-south-1.json
cfnlint/data/CloudSpecs/ap-south-2.json
cfnlint/data/CloudSpecs/ap-southeast-1.json
cfnlint/data/CloudSpecs/ap-southeast-2.json
cfnlint/data/CloudSpecs/ap-southeast-3.json
cfnlint/data/CloudSpecs/ap-southeast-4.json
cfnlint/data/CloudSpecs/ap-southeast-5.json
cfnlint/data/CloudSpecs/ca-central-1.json
cfnlint/data/CloudSpecs/ca-west-1.json
cfnlint/data/CloudSpecs/cn-north-1.json
cfnlint/data/CloudSpecs/cn-northwest-1.json
cfnlint/data/CloudSpecs/eu-central-1.json
cfnlint/data/CloudSpecs/eu-central-2.json
cfnlint/data/CloudSpecs/eu-north-1.json
cfnlint/data/CloudSpecs/eu-south-1.json
cfnlint/data/CloudSpecs/eu-south-2.json
cfnlint/data/CloudSpecs/eu-west-1.json
cfnlint/data/CloudSpecs/eu-west-2.json
cfnlint/data/CloudSpecs/eu-west-3.json
cfn_lint-0.87.11.dist-info/LICENSE
cfn_lint-0.87.11.dist-info/METADATA
cfn_lint-0.87.11.dist-info/NOTICE
cfn_lint-0.87.11.dist-info/WHEEL
cfn_lint-0.87.11.dist-info/entry_points.txt
cfn_lint-0.87.11.dist-info/top_level.txt
cfn_lint-0.87.11.dist-info/RECORD
