Metadata-Version: 2.1
Name: cfn-lint
Version: 0.87.11
Summary: Checks CloudFormation templates for practices and behaviour that could potentially be improved
Home-page: https://github.com/aws-cloudformation/cfn-python-lint
Author: kddejong
Author-email: kddejong@amazon.com
License: MIT no attribution
Keywords: aws,lint
Classifier: Development Status :: 5 - Production/Stable
Classifier: Intended Audience :: Developers
Classifier: License :: OSI Approved :: MIT License
Classifier: Natural Language :: English
Classifier: Operating System :: OS Independent
Classifier: Programming Language :: Python :: 3
Classifier: Programming Language :: Python :: 3.8
Classifier: Programming Language :: Python :: 3.9
Classifier: Programming Language :: Python :: 3.10
Classifier: Programming Language :: Python :: 3.11
Classifier: Programming Language :: Python :: 3.12
Requires-Python: >=3.8, <=4.0, !=4.0
License-File: LICENSE
License-File: NOTICE
Requires-Dist: pyyaml>5.4
Requires-Dist: aws-sam-translator>=1.91.0
Requires-Dist: jsonpatch
Requires-Dist: jsonschema<5,>=3.0
Requires-Dist: networkx<4,>=2.4
Requires-Dist: junit-xml~=1.9
Requires-Dist: jschema-to-python~=1.2.3
Requires-Dist: sarif-om~=1.0.4
Requires-Dist: sympy>=1.0.0
Requires-Dist: regex>=2021.7.1
